<annotation>
	<folder>test1i</folder>
	<filename>41.jpg</filename>
	<path>/home/ping/Desktop/object_detection_demo/data/images/test1i/41.jpg</path>
	<source>
		<database>Unknown</database>
	</source>
	<size>
		<width>800</width>
		<height>600</height>
		<depth>3</depth>
	</size>
	<segmented>0</segmented>
	<object>
		<name>crack</name>
		<pose>Unspecified</pose>
		<truncated>0</truncated>
		<difficult>0</difficult>
		<bndbox>
			<xmin>7</xmin>
			<ymin>40</ymin>
			<xmax>791</xmax>
			<ymax>394</ymax>
		</bndbox>
	</object>
	<object>
		<name>crack</name>
		<pose>Unspecified</pose>
		<truncated>0</truncated>
		<difficult>0</difficult>
		<bndbox>
			<xmin>618</xmin>
			<ymin>23</ymin>
			<xmax>789</xmax>
			<ymax>173</ymax>
		</bndbox>
	</object>
	<object>
		<name>crack</name>
		<pose>Unspecified</pose>
		<truncated>0</truncated>
		<difficult>0</difficult>
		<bndbox>
			<xmin>13</xmin>
			<ymin>8</ymin>
			<xmax>183</xmax>
			<ymax>73</ymax>
		</bndbox>
	</object>
</annotation>
